NREP/__init__.py
NREP/beacon/__init__.py
NREP/bridge/http2nrep/__init__.py
NREP/core/NREPClient.py
NREP/core/VersionControl.py
NREP/core/__init__.py
NREP/core/package.py
NREP/node/__init__.py
NREP/node/pipe.py
NREP/utils/__init__.py
NREP/utils/logpong.py
NREP/utils/spec.py
NREP-0.1.2.post2.dist-info/METADATA
NREP-0.1.2.post2.dist-info/WHEEL
NREP-0.1.2.post2.dist-info/top_level.txt
NREP-0.1.2.post2.dist-info/RECORD
